TranscriptSim/Class.py
TranscriptSim/__init__.py
TranscriptSim-0.0.12.dist-info/LICENSE
TranscriptSim-0.0.12.dist-info/METADATA
TranscriptSim-0.0.12.dist-info/WHEEL
TranscriptSim-0.0.12.dist-info/top_level.txt
TranscriptSim-0.0.12.dist-info/RECORD
