Metadata-Version: 2.1
Name: TranscriptSim
Version: 0.0.12
Summary: Package for Coaching Session Transcripts Similarity Calculations
Home-page: https://github.com/congxinxu0116/TranscriptSim
Author: Ashley Scurlock, Kip McCharen, Latifa Hasan, Congxin (David) Xu, Kylie Anglin
Author-email: anglin@hey.com
License: UNKNOWN
Project-URL: Bug Tracker, https://github.com/congxinxu0116/TranscriptSim
Platform: UNKNOWN
Classifier: Programming Language :: Python :: 3
Classifier: License :: OSI Approved :: MIT License
Classifier: Operating System :: OS Independent
Requires-Python: >=3.6
